{
  "primarytemporalquery": 0,
  "bitemporalsimilarityquery": {
    "keywordquery": {
      "formerquery": {
        "synsetgroups": []
      },
      "latterquery": {
        "synsetgroups": []
      }
    },
    "colorsketchquery": {
      "formerquery": {
        "canvaswidth": 216,
        "canvasheight": 384,
        "colorsketchellipses": [
          {
            "ellipsestate": 0,
            "positionx": 0.15166548547129696,
            "positiony": 0.074084573588471744,
            "horizontalaxis": 0.64209780297661223,
            "verticalaxis": 0.20663044334199535,
            "rotation": 0,
            "colorr": 51,
            "colorg": 194,
            "colorb": 255
          },
          {
            "ellipsestate": 0,
            "positionx": 0.41672572643515227,
            "positiony": 0.60829986613119136,
            "horizontalaxis": 0.53437278525868159,
            "verticalaxis": 0.36034333412079678,
            "rotation": 0,
            "colorr": 153,
            "colorg": 46,
            "colorb": 0
          }
        ]
      },
      "latterquery": {
        "canvaswidth": 216,
        "canvasheight": 384,
        "colorsketchellipses": [
          {
            "ellipsestate": 0,
            "positionx": 0.22537207654145996,
            "positiony": 0.44742105677612448,
            "horizontalaxis": 0.038270729978738482,
            "verticalaxis": 0.60981179620442616,
            "rotation": 0,
            "colorr": 255,
            "colorg": 255,
            "colorb": 255
          }
        ]
      }
    },
    "facesketchquery": {
      "formerquery": {
        "canvaswidth": 216,
        "canvasheight": 384,
        "colorsketchellipses": []
      },
      "latterquery": {
        "canvaswidth": 216,
        "canvasheight": 384,
        "colorsketchellipses": []
      }
    },
    "textsketchquery": {
      "formerquery": {
        "canvaswidth": 216,
        "canvasheight": 384,
        "colorsketchellipses": []
      },
      "latterquery": {
        "canvaswidth": 216,
        "canvasheight": 384,
        "colorsketchellipses": []
      }
    },
    "semanticexamplequery": {
      "formerquery": {
        "positiveexampleids": [],
        "negativeexampleids": [],
        "externalimages": []
      },
      "latterquery": {
        "positiveexampleids": [],
        "negativeexampleids": [],
        "externalimages": []
      }
    }
  },
  "formerfusionquery": {
    "sortingsimilaritymodel": 1,
    "keywordfilteringquery": {
      "filterstate": 2,
      "threshold": 0.5
    },
    "colorsketchfilteringquery": {
      "filterstate": 0,
      "threshold": 0.22518652637443573
    },
    "facesketchfilteringquery": {
      "filterstate": 2,
      "threshold": 0.22518652637443573
    },
    "textsketchfilteringquery": {
      "filterstate": 2,
      "threshold": 0.22518652637443573
    },
    "semanticexamplefilteringquery": {
      "filterstate": 2,
      "threshold": 0.3
    }
  },
  "latterfusionquery": {
    "sortingsimilaritymodel": 1,
    "keywordfilteringquery": {
      "filterstate": 2,
      "threshold": 0.5
    },
    "colorsketchfilteringquery": {
      "filterstate": 0,
      "threshold": 0.1
    },
    "facesketchfilteringquery": {
      "filterstate": 2,
      "threshold": 0.1
    },
    "textsketchfilteringquery": {
      "filterstate": 2,
      "threshold": 0.1
    },
    "semanticexamplefilteringquery": {
      "filterstate": 2,
      "threshold": 0.3
    }
  },
  "formerfilteringquery": {
    "colorsaturationquery": {
      "filterstate": 2,
      "threshold": 0.9
    },
    "percentofblackquery": {
      "filterstate": 2,
      "threshold": 0.65
    },
    "countfilteringquery": {
      "filterstate": 0,
      "maxpervideo": 3,
      "maxpershot": 1,
      "maxpergroup": -1
    }
  },
  "latterfilteringquery": {
    "colorsaturationquery": {
      "filterstate": 2,
      "threshold": 0.9
    },
    "percentofblackquery": {
      "filterstate": 2,
      "threshold": 0.65
    },
    "countfilteringquery": {
      "filterstate": 0,
      "maxpervideo": 3,
      "maxpershot": 1,
      "maxpergroup": -1
    }
  }
}